LICENSE
hx_requests/.gitignore
hx_requests/__init__.py
hx_requests/apps.py
hx_requests/django_views.py
hx_requests/hx_registry.py
hx_requests/hx_requests.py
hx_requests/security_utils.py
hx_requests/static/hx_requests/css/modal.css
hx_requests/templatetags/__init__.py
hx_requests/templatetags/hx_tags.py
hx_requests/utils.py
hx_requests/views.py
hx_requests-0.40.1.dist-info/LICENSE
hx_requests-0.40.1.dist-info/METADATA
hx_requests-0.40.1.dist-info/WHEEL
hx_requests-0.40.1.dist-info/RECORD
