Metadata-Version: 2.1
Name: hx-requests
Version: 0.40.1
Summary: Facilitates the usage of HTMX with Django
Home-page: https://github.com/yaakovLowenstein/hx-requests
License: MIT
Keywords: django,htmx
Author: yaakovLowenstein
Author-email: lowensteinyaakov@gmail.com
Requires-Python: >=3.8,<4.0
Classifier: Environment :: Web Environment
Classifier: Framework :: Django
Classifier: Framework :: Django :: 3.2
Classifier: Framework :: Django :: 4.0
Classifier: Framework :: Django :: 4.1
Classifier: Intended Audience :: Developers
Classifier: License :: OSI Approved :: MIT License
Classifier: Operating System :: OS Independent
Classifier: Programming Language :: Python
Classifier: Programming Language :: Python :: 3
Classifier: Programming Language :: Python :: 3.8
Classifier: Programming Language :: Python :: 3.9
Classifier: Programming Language :: Python :: 3.10
Classifier: Programming Language :: Python :: 3.11
Classifier: Programming Language :: Python :: 3.12
Classifier: Programming Language :: Python :: 3.13
Requires-Dist: Django (>=3.2)
Requires-Dist: django-render-block (>=0.10,<0.11)
Project-URL: Repository, https://github.com/yaakovLowenstein/hx-requests
